client.py
smart_shell-0.0.3.dist-info/LICENSE
smart_shell-0.0.3.dist-info/METADATA
smart_shell-0.0.3.dist-info/WHEEL
smart_shell-0.0.3.dist-info/entry_points.txt
smart_shell-0.0.3.dist-info/top_level.txt
smart_shell-0.0.3.dist-info/RECORD
