Metadata-Version: 2.1
Name: smart-shell
Version: 0.0.3
Summary: AI command line tools
Home-page: https://github.com/joseph-mcallister/smart-shell
Author: Joe McAllister
Author-email: joseph.l.mcallister+smart-shell@gmail.com
License: GNU GENERAL PUBLIC LICENSE
Platform: UNKNOWN
Classifier: Programming Language :: Python :: 3.8
Classifier: Operating System :: OS Independent
Requires-Python: >=3.7
License-File: LICENSE
Requires-Dist: altgraph (==0.17.2)
Requires-Dist: certifi (==2021.5.30)
Requires-Dist: charset-normalizer (==2.0.6)
Requires-Dist: idna (==3.2)
Requires-Dist: macholib (==1.15.2)
Requires-Dist: pyinstaller (==4.5.1)
Requires-Dist: pyinstaller-hooks-contrib (==2021.3)
Requires-Dist: requests (==2.26.0)
Requires-Dist: urllib3 (==1.26.6)
Requires-Dist: psutil (==5.8.0)
